{"expr":{"type":"witness","id":5},"constraints":[{"type":"eq","b":{"type":"witness","id":5},"a":{"type":"add","b":{"val":"5","type":"lit"},"a":{"val":"4","type":"lit"}}},{"type":"eq","b":{"val":"1","type":"lit"},"a":{"type":"witness","id":4}},{"type":"eq","b":{"val":"0","type":"lit"},"a":{"type":"mul","b":{"type":"sub","b":{"type":"witness","id":4},"a":{"val":"1","type":"lit"}},"a":{"type":"witness","id":4}}},{"type":"eq","b":{"val":"0","type":"lit"},"a":{"type":"mul","b":{"type":"sub","b":{"type":"witness","id":4},"a":{"val":"1","type":"lit"}},"a":{"type":"witness","id":4}}},{"type":"eq","b":{"val":"0","type":"lit"},"a":{"type":"mul","b":{"type":"sub","b":{"val":"8","type":"lit"},"a":{"type":"witness","id":3}},"a":{"type":"witness","id":4}}},{"type":"eq","b":{"type":"witness","id":3},"a":{"type":"mul","b":{"val":"4","type":"lit"},"a":{"val":"2","type":"lit"}}},{"type":"eq","b":{"type":"witness","id":2},"a":{"type":"mul","b":{"val":"2","type":"lit"},"a":{"val":"3","type":"lit"}}},{"type":"eq","b":{"val":"1","type":"lit"},"a":{"type":"witness","id":1}},{"type":"eq","b":{"val":"0","type":"lit"},"a":{"type":"mul","b":{"type":"sub","b":{"type":"witness","id":1},"a":{"val":"1","type":"lit"}},"a":{"type":"witness","id":1}}},{"type":"eq","b":{"val":"0","type":"lit"},"a":{"type":"mul","b":{"type":"sub","b":{"type":"witness","id":1},"a":{"val":"1","type":"lit"}},"a":{"type":"witness","id":1}}},{"type":"eq","b":{"val":"0","type":"lit"},"a":{"type":"mul","b":{"type":"sub","b":{"val":"5","type":"lit"},"a":{"type":"witness","id":0}},"a":{"type":"witness","id":1}}},{"type":"eq","b":{"type":"witness","id":0},"a":{"type":"add","b":{"val":"3","type":"lit"},"a":{"val":"2","type":"lit"}}}]}